circular_optimizer/__init__.py
circular_optimizer/circular.py
circular_optimizer/utils.py
circular_optimizer-0.1.0.dist-info/METADATA
circular_optimizer-0.1.0.dist-info/WHEEL
circular_optimizer-0.1.0.dist-info/top_level.txt
circular_optimizer-0.1.0.dist-info/RECORD
