Metadata-Version: 2.4
Name: circular-optimizer
Version: 0.1.0
Summary: Gradient-based optimizer with circular exploration
Author: isa
Requires-Python: >=3.8
Requires-Dist: torch
Dynamic: author
Dynamic: requires-dist
Dynamic: requires-python
Dynamic: summary
